hello_robot_stretch_body_tools-0.7.15.data/scripts/stretch_about.py
hello_robot_stretch_body_tools-0.7.15.data/scripts/stretch_about_text.py
hello_robot_stretch_body_tools-0.7.15.data/scripts/stretch_arm_home.py
hello_robot_stretch_body_tools-0.7.15.data/scripts/stretch_arm_jog.py
hello_robot_stretch_body_tools-0.7.15.data/scripts/stretch_audio_test.py
hello_robot_stretch_body_tools-0.7.15.data/scripts/stretch_base_jog.py
hello_robot_stretch_body_tools-0.7.15.data/scripts/stretch_camera_streams_check.py
hello_robot_stretch_body_tools-0.7.15.data/scripts/stretch_configure_tool.py
hello_robot_stretch_body_tools-0.7.15.data/scripts/stretch_dex_wrist_float.py
hello_robot_stretch_body_tools-0.7.15.data/scripts/stretch_dex_wrist_jog.py
hello_robot_stretch_body_tools-0.7.15.data/scripts/stretch_free_robot_process.py
hello_robot_stretch_body_tools-0.7.15.data/scripts/stretch_gamepad_teleop.py
hello_robot_stretch_body_tools-0.7.15.data/scripts/stretch_gripper_home.py
hello_robot_stretch_body_tools-0.7.15.data/scripts/stretch_gripper_jog.py
hello_robot_stretch_body_tools-0.7.15.data/scripts/stretch_hardware_echo.py
hello_robot_stretch_body_tools-0.7.15.data/scripts/stretch_head_jog.py
hello_robot_stretch_body_tools-0.7.15.data/scripts/stretch_lift_home.py
hello_robot_stretch_body_tools-0.7.15.data/scripts/stretch_lift_jog.py
hello_robot_stretch_body_tools-0.7.15.data/scripts/stretch_params.py
hello_robot_stretch_body_tools-0.7.15.data/scripts/stretch_pimu_jog.py
hello_robot_stretch_body_tools-0.7.15.data/scripts/stretch_pimu_scope.py
hello_robot_stretch_body_tools-0.7.15.data/scripts/stretch_realsense_visualizer.py
hello_robot_stretch_body_tools-0.7.15.data/scripts/stretch_respeaker_test.py
hello_robot_stretch_body_tools-0.7.15.data/scripts/stretch_robot_battery_check.py
hello_robot_stretch_body_tools-0.7.15.data/scripts/stretch_robot_collision_visualizer.py
hello_robot_stretch_body_tools-0.7.15.data/scripts/stretch_robot_dynamixel_reboot.py
hello_robot_stretch_body_tools-0.7.15.dist-info/licenses/LICENSE.md
hello_robot_stretch_body_tools-0.7.15.dist-info/METADATA
hello_robot_stretch_body_tools-0.7.15.dist-info/WHEEL
hello_robot_stretch_body_tools-0.7.15.dist-info/top_level.txt
hello_robot_stretch_body_tools-0.7.15.dist-info/RECORD
