Metadata-Version: 2.4
Name: hello-robot-stretch-body-tools
Version: 0.7.15
Summary: Stretch Body Tools
Home-page: https://github.com/hello-robot/stretch_body
Author: Hello Robot Inc
Author-email: support@hello-robot.com
Classifier: Programming Language :: Python :: 3
Classifier: Operating System :: OS Independent
Classifier: License :: OSI Approved :: Apache Software License
License-File: LICENSE.md
Requires-Dist: numpy>=1.24
Requires-Dist: scipy
Requires-Dist: matplotlib
Requires-Dist: ipython
Requires-Dist: pandas
Requires-Dist: sympy
Requires-Dist: nose
Requires-Dist: sh
Requires-Dist: packaging
Requires-Dist: inputs
Requires-Dist: drawnow
Requires-Dist: rplidar-roboticia
Requires-Dist: snakeviz
Requires-Dist: pyusb
Requires-Dist: SpeechRecognition
Requires-Dist: pixel-ring
Requires-Dist: click
Requires-Dist: cma
Requires-Dist: opencv-contrib-python
Requires-Dist: colorama
Requires-Dist: scikit-image
Requires-Dist: open3d
Requires-Dist: pyrealsense2
Requires-Dist: gitpython
Requires-Dist: xmltodict
Requires-Dist: filelock
Requires-Dist: pyaudio
Requires-Dist: pyglet==1.4.10; python_version < "3.0"
Requires-Dist: trimesh==4.4.7
Requires-Dist: urchin
Requires-Dist: pyyaml>=5.1
Dynamic: author
Dynamic: author-email
Dynamic: classifier
Dynamic: description
Dynamic: description-content-type
Dynamic: home-page
Dynamic: license-file
Dynamic: requires-dist
Dynamic: summary
